mopidy_homeassistant/__init__.py
mopidy_homeassistant/extension.py
mopidy_homeassistant/mixer.py
mopidy_homeassistant_mixer-0.1.3.dist-info/METADATA
mopidy_homeassistant_mixer-0.1.3.dist-info/WHEEL
mopidy_homeassistant_mixer-0.1.3.dist-info/entry_points.txt
mopidy_homeassistant_mixer-0.1.3.dist-info/top_level.txt
mopidy_homeassistant_mixer-0.1.3.dist-info/RECORD
