Metadata-Version: 2.4
Name: mopidy-homeassistant-mixer
Version: 0.1.3
Summary: Mopidy mixer for Home Assistant media player control
Home-page: https://github.com/gorzelak/mopidy-homeassistant-mixer
Author: Krzysztof Gorzelak
Author-email: gorzelak@users.noreply.github.com
Requires-Dist: mopidy>=3.0
Requires-Dist: requests
Requires-Dist: websockets
Dynamic: author
Dynamic: author-email
Dynamic: description
Dynamic: description-content-type
Dynamic: home-page
Dynamic: requires-dist
Dynamic: summary
